LICENSE
MANIFEST.in
README.md
setup.py
toyplot/__init__.py
toyplot/bitmap.py
toyplot/broadcast.py
toyplot/browser.py
toyplot/canvas.py
toyplot/cars.csv
toyplot/color.py
toyplot/community-assigned.csv
toyplot/community-edges.csv
toyplot/community-truth.csv
toyplot/commute.csv
toyplot/config.py
toyplot/coordinates.py
toyplot/data.py
toyplot/deliveries.csv
toyplot/font.py
toyplot/format.py
toyplot/html.py
toyplot/layout.py
toyplot/locator.py
toyplot/mark.py
toyplot/marker.py
toyplot/mp4.py
toyplot/pdf.py
toyplot/png.py
toyplot/projection.py
toyplot/require.py
toyplot/scenegraph.py
toyplot/style.py
toyplot/svg.py
toyplot/temperatures.csv
toyplot/text.py
toyplot/transform.py
toyplot/units.py
toyplot.egg-info/PKG-INFO
toyplot.egg-info/SOURCES.txt
toyplot.egg-info/dependency_links.txt
toyplot.egg-info/requires.txt
toyplot.egg-info/top_level.txt
toyplot/reportlab/__init__.py
toyplot/reportlab/pdf.py
toyplot/reportlab/png.py