Metadata-Version: 2.1
Name: toyplot
Version: 1.0.2
Summary: A modern plotting toolkit supporting electronic publishing and reproducibility.
Home-page: http://toyplot.readthedocs.io
Author: Timothy M. Shead
Author-email: tshead@sandia.gov
Maintainer: Timothy M. Shead
Maintainer-email: tshead@sandia.gov
License: UNKNOWN
Project-URL: Chat, https://github.com/sandialabs/toyplot/discussions
Project-URL: Coverage, https://coveralls.io/r/sandialabs/toyplot
Project-URL: Documentation, https://toyplot.readthedocs.io
Project-URL: Issue Tracker, https://github.com/sandialabs/toyplot/issues
Project-URL: Regression Tests, https://github.com/sandialabs/toyplot/actions
Project-URL: Source, https://github.com/sandialabs/toyplot
Platform: UNKNOWN
Classifier: Development Status :: 5 - Production/Stable
Classifier: Environment :: Console
Classifier: Environment :: Other Environment
Classifier: Environment :: Web Environment
Classifier: Framework :: IPython
Classifier: Intended Audience :: Science/Research
Classifier: License :: OSI Approved :: BSD License
Classifier: Natural Language :: English
Classifier: Programming Language :: Python :: 3
Classifier: Topic :: Scientific/Engineering :: Visualization
License-File: LICENSE
